Metadata-Version: 1.1
Name: pymor-nb2plots
Version: 0.4
Summary: Converting between ipython notebooks and sphinx docs
Home-page: http://github.com/matthew-brett/nb2plots
Author: Matthew Brett
Author-email: matthew.brett@gmail.com
License: BSD license
Platform: UNKNOWN
Classifier: Development Status :: 2 - Pre-Alpha
Classifier: Environment :: Console
Classifier: Intended Audience :: Developers
Classifier: Intended Audience :: Science/Research
Classifier: License :: OSI Approved :: BSD License
Classifier: Programming Language :: Python
Classifier: Programming Language :: Python :: 3
Classifier: Topic :: Scientific/Engineering
Classifier: Operating System :: Microsoft :: Windows
Classifier: Operating System :: POSIX
Classifier: Operating System :: Unix
Classifier: Operating System :: MacOS
